imio.news.policy-1.1.8-py3.12-nspkg.pth
imio/news/policy/__init__.py
imio/news/policy/configure.zcml
imio/news/policy/interfaces.py
imio/news/policy/permissions.zcml
imio/news/policy/setuphandlers.py
imio/news/policy/subscribers.zcml
imio/news/policy/testing.py
imio/news/policy/utils.py
imio/news/policy/browser/__init__.py
imio/news/policy/browser/configure.zcml
imio/news/policy/browser/overrides/.gitkeep
imio/news/policy/browser/static/.gitkeep
imio/news/policy/profiles/default/actions.xml
imio/news/policy/profiles/default/browserlayer.xml
imio/news/policy/profiles/default/metadata.xml
imio/news/policy/profiles/default/viewlets.xml
imio/news/policy/profiles/default/registry/autopublishing.xml
imio/news/policy/profiles/default/registry/caching.xml
imio/news/policy/profiles/default/registry/news.xml
imio/news/policy/profiles/default/types/Collection.xml
imio/news/policy/profiles/default/types/Document.xml
imio/news/policy/profiles/default/types/Event.xml
imio/news/policy/profiles/default/types/File.xml
imio/news/policy/profiles/default/types/Folder.xml
imio/news/policy/profiles/default/types/Image.xml
imio/news/policy/profiles/default/types/Link.xml
imio/news/policy/profiles/default/types/News_Item.xml
imio/news/policy/profiles/default/types/Plone_site.xml
imio/news/policy/profiles/uninstall/browserlayer.xml
imio/news/policy/tests/__init__.py
imio/news/policy/tests/test_robot.py
imio/news/policy/tests/test_setup.py
imio/news/policy/tests/robot/test_example.robot
imio/news/policy/upgrades/__init__.py
imio/news/policy/upgrades/configure.zcml
imio/news/policy/upgrades/upgrades.py
imio/news/policy/upgrades/profiles/1000_to_1001/browserlayer.xml
imio/news/policy/upgrades/profiles/1001_to_1002/registry/autopublishing.xml
imio/news/policy/upgrades/profiles/1002_to_1003/actions.xml
imio/news/policy/upgrades/profiles/1003_to_1004/registry/caching.xml
imio/news/policy/upgrades/profiles/1004_to_1005/registry/caching.xml
imio_news_policy-1.1.8.dist-info/licenses/LICENSE.GPL
imio_news_policy-1.1.8.dist-info/licenses/LICENSE.rst
imio_news_policy-1.1.8.dist-info/METADATA
imio_news_policy-1.1.8.dist-info/WHEEL
imio_news_policy-1.1.8.dist-info/namespace_packages.txt
imio_news_policy-1.1.8.dist-info/top_level.txt
imio_news_policy-1.1.8.dist-info/RECORD
